kkScript/__init__.py
kkScript/kkdb.py
kkScript-1.0.1.dist-info/LICENSE
kkScript-1.0.1.dist-info/METADATA
kkScript-1.0.1.dist-info/WHEEL
kkScript-1.0.1.dist-info/top_level.txt
kkScript-1.0.1.dist-info/RECORD
