Metadata-Version: 2.1
Name: kkScript
Version: 1.0.1
Summary: Simple database with own programming languge.
Author-email: EasyOmny <omenplay325@gmail.com>
License: Copyright (c) 2023 EasyOmny
Project-URL: Homepage, https://github.com/EasyOmny/kkscript
Keywords: python,database,language
Classifier: License :: OSI Approved :: MIT License
Classifier: Programming Language :: Python
Classifier: Programming Language :: Python :: 3
Requires-Python: >=3.9
License-File: LICENSE
